MANIFEST.in
README.rst
setup.cfg
setup.py
bin/text2img
bin/text2img.cmd
text2img/__init__.py
text2img/clips.py
text2img/gthemes.py
text2img/svgmanager.py
text2img/tool.py
text2img.egg-info/PKG-INFO
text2img.egg-info/SOURCES.txt
text2img.egg-info/dependency_links.txt
text2img.egg-info/not-zip-safe
text2img.egg-info/requires.txt
text2img.egg-info/top_level.txt