Metadata-Version: 1.1
Name: text2img
Version: 0.0.59
Summary: Python library for generate images from text.
Home-page: https://github.com/tuaplicacionpropia/text2img
Author: tuaplicacionpropia.com
Author-email: tuaplicacionpropia@gmail.com
License: MIT
Download-URL: https://github.com/tuaplicacionpropia/text2img/archive/master.zip
Keywords: svg,text,json,generator
Platform: any
Classifier: Development Status :: 4 - Beta
Classifier: License :: OSI Approved :: MIT License
Classifier: Programming Language :: Python
Classifier: Programming Language :: Python :: 2.7
Classifier: Intended Audience :: Developers
Classifier: Topic :: Multimedia :: Graphics
